st_copy_to_clipboard/__init__.py
st_copy_to_clipboard/frontend/index.html
st_copy_to_clipboard/frontend/main.js
st_copy_to_clipboard/frontend/streamlit-component-lib.js
st_copy_to_clipboard/frontend/style.css
st_copy_to_clipboard-0.1.6.dist-info/LICENSE
st_copy_to_clipboard-0.1.6.dist-info/METADATA
st_copy_to_clipboard-0.1.6.dist-info/WHEEL
st_copy_to_clipboard-0.1.6.dist-info/top_level.txt
st_copy_to_clipboard-0.1.6.dist-info/RECORD
