Metadata-Version: 2.1
Name: st-copy-to-clipboard
Version: 0.1.6
Summary: Streamlit component that allows you to copy text to the clipboard.
Home-page: https://github.com/mmz-001/st-copy-to-clipboard
Author: mmz-001
Author-email: mmzappdev@gmail.com
Requires-Python: >=3.7
License-File: LICENSE
